openpyxl_grid/__init__.py
openpyxl_grid/grid.py
openpyxl_grid/xl/__init__.py
openpyxl_grid/xl/xgrid.py
openpyxl_grid/xl/xlocation.py
openpyxl_grid/xl/xoper.py
openpyxl_grid/xl/xstyle.py
openpyxl_grid-0.0.21.dist-info/METADATA
openpyxl_grid-0.0.21.dist-info/WHEEL
openpyxl_grid-0.0.21.dist-info/licenses/LICENSE
openpyxl_grid-0.0.21.dist-info/RECORD
