Metadata-Version: 2.1
Name: openpyxl_grid
Version: 0.0.21
Summary: An auto grid filler module for excel based on openpyxl lib.
Project-URL: Homepage, https://github.com/sitwjn/openpyxl-grid
Project-URL: Bug Tracker, https://github.com/sitwjn/openpyxl-grid/issues
Author-email: Jianai Wang <sitwjn@163.com>
License-File: LICENSE
Classifier: License :: OSI Approved :: MIT License
Classifier: Operating System :: OS Independent
Classifier: Programming Language :: Python :: 3
Requires-Python: >=3.7
Requires-Dist: datetime
Requires-Dist: null
Requires-Dist: openpyxl
